wagtail_adminsortable/__init__.py
wagtail_adminsortable/admin.py
wagtail_adminsortable/apps.py
wagtail_adminsortable/defaults.py
wagtail_adminsortable/forms.py
wagtail_adminsortable/mixins.py
wagtail_adminsortable/models.py
wagtail_adminsortable/views.py
wagtail_adminsortable/static/js/adminsortable/jquery.ui.touch-punch.min.js
wagtail_adminsortable/templates/adminsortable/index.html
wagtail_adminsortable/templates/adminsortable/includes/result_list.html
wagtail_adminsortable/templatetags/__init__.py
wagtail_adminsortable/templatetags/adminsortable_tags.py
wagtail_adminsortable-0.1.dist-info/METADATA
wagtail_adminsortable-0.1.dist-info/WHEEL
wagtail_adminsortable-0.1.dist-info/top_level.txt
wagtail_adminsortable-0.1.dist-info/RECORD
